{"sport": "NFL", "type": "Draft", "ranking_type_name": "draft", "year": "2021", "week": "0", "position_id": "K", "scoring": "STD", "filters": "7,9,22,23,44,45,66,145,220,285,329,394,453,454,562,689,699,714,908,927,1075,1136,1138,1147,1172,1507,1549,1661,1715,2551,2598,2715,2716,2855,2889,2915,3096,3112,3346,3396,3464,3603,3604,3612,4170", "count": 43, "total_experts": 45, "last_updated": "8/20", "players": [{"player_id": 11465, "player_name": "Justin Tucker", "sportsdata_id": "20a0bad2-d530-4ff4-a2df-5c0a21a1f5db", "player_team_id": "BAL", "player_position_id": "K", "player_positions": "K", "player_short_name": "J. Tucker", "player_eligibility": "K", "player_yahoo_positions": "K", "player_page_url": "https://www.fantasypros.com/nfl/players/justin-tucker.php", "player_filename": "justin-tucker.php", "player_square_image_url": "https://images.fantasypros.com/images/players/nfl/11465/headshot/210x210.png", "player_image_url": "https://images.fantasypros.com/images/players/nfl/11465/headshot/210x210.png", "player_yahoo_id": "26534", "cbs_player_id": "1985374", "player_bye_week": "8", "player_owned_avg": 99.7, "player_owned_espn": 99.3, "player_owned_yahoo": 100, "player_ecr_delta": null, "rank_ecr": 1, "rank_min": "1", "rank_max": "4", "rank_ave": "1.57", "rank_std": "0.85", "pos_rank": "K1", "tier": 1}, {"player_id": 16712, "player_name": "Harrison Butker", "sportsdata_id": "4ceb866c-8eaf-49b5-9043-56228e43a2e5", "player_team_id": "KC", "player_position_id": "K", "player_positions": "K", "player_short_name": "H. Butker", "player_eligibility": "K", "player_yahoo_positions": "K", "player_page_url": "https://www.fantasypros.com/nfl/players/harrison-butker.php", "player_filename": "harrison-butker.php", "player_square_image_url": "https://images.fantasypros.com/images/players/nfl/16712/headshot/210x210.png", "player_image_url": "https://images.fantasypros.com/images/players/nfl/16712/headshot/210x210.png", "player_yahoo_id": "30346", "cbs_player_id": "2078888", "player_bye_week": "12", "player_owned_avg": 99.3, "player_owned_espn": 99.5, "player_owned_yahoo": 99, "player_ecr_delta": null, "rank_ecr": 2, "rank_min": "1", "rank_max": "5", "rank_ave": "2.24", "rank_std": "1.13", "pos_rank": "K2", "tier": 1}, {"player_id": 16910, "player_name": "Younghoe Koo", "sportsdata_id": "a8c79523-3d0e-48dd-b4c6-e3d8afd24a13", "player_team_id": "ATL", "player_position_id": "K", "player_positions": "K", "player_short_name": "Y. Koo", "player_eligibility": "K", "player_yahoo_positions": "K", "player_page_url": "https://www.fantasypros.com/nfl/players/younghoe-koo.php", "player_filename": "younghoe-koo.php", "player_square_image_url": "https://images.fantasypros.com/images/players/nfl/16910/headshot/210x210.png", "player_image_url": "https://images.fantasypros.com/images/players/nfl/16910/headshot/210x210.png", "player_yahoo_id": "30426", "cbs_player_id": "2820093", "player_bye_week": "6", "player_owned_avg": 96.3, "player_owned_espn": 94.5, "player_owned_yahoo": 98, "player_ecr_delta": null, "rank_ecr": 3, "rank_min": "1", "rank_max": "8", "rank_ave": "3.90", "rank_std": "1.87", "pos_rank": "K3", "tier": 1}, {"player_id": 11345, "player_name": "Greg Zuerlein", "sportsdata_id": "93d11276-45d2-4168-a9b7-df0cbf12dabb", "player_team_id": "DAL", "player_position_id": "K", "player_positions": "K", "player_short_name": "G. Zuerlein", "player_eligibility": "K", "player_yahoo_positions": "K", "player_page_url": "https://www.fantasypros.com/nfl/players/greg-zuerlein.php", "player_filename": "greg-zuerlein.php", "player_square_image_url": "https://images.fantasypros.com/images/players/nfl/11345/headshot/210x210.png", "player_image_url": "https://images.fantasypros.com/images/players/nfl/11345/headshot/210x210.png", "player_yahoo_id": "25881", "cbs_player_id": "1971893", "player_bye_week": "7", "player_owned_avg": 63, "player_owned_espn": 51, "player_owned_yahoo": 75, "player_ecr_delta": null, "rank_ecr": 4, "rank_min": "2", "rank_max": "11", "rank_ave": "4.81", "rank_std": "1.97", "pos_rank": "K4", "tier": 1}, {"player_id": 17533, "player_name": "Jason Sanders", "sportsdata_id": "5ffb654f-0de5-424b-aa2f-ad511deb5b51", "player_team_id": "MIA", "player_position_id": "K", "player_positions": "K", "player_short_name": "J. Sanders", "player_eligibility": "K", "player_yahoo_positions": "K", "player_page_url": "https://www.fantasypros.com/nfl/players/jason-sanders.php", "player_filename": "jason-sanders.php", "player_square_image_url": "https://images.fantasypros.com/images/players/nfl/17533/headshot/210x210.png", "player_image_url": "https://images.fantasypros.com/images/players/nfl/17533/headshot/210x210.png", "player_yahoo_id": "31199", "cbs_player_id": "2131909", "player_bye_week": "14", "player_owned_avg": 84, "player_owned_espn": 88.9, "player_owned_yahoo": 79, "player_ecr_delta": null, "rank_ecr": 5, "rank_min": "3", "rank_max": "11", "rank_ave": "6.36", "rank_std": "2.30", "pos_rank": "K5", "tier": 2}, {"player_id": 19760, "player_name": "Tyler Bass", "sportsdata_id": "bfccbff4-bc01-41ed-aa11-be976160504c", "player_team_id": "BUF", "player_position_id": "K", "player_positions": "K", "player_short_name": "T. Bass", "player_eligibility": "K", "player_yahoo_positions": "K", "player_page_url": "https://www.fantasypros.com/nfl/players/tyler-bass.php", "player_filename": "tyler-bass.php", "player_square_image_url": "https://images.fantasypros.com/images/players/nfl/19760/headshot/210x210.png", "player_image_url": "https://images.fantasypros.com/images/players/nfl/19760/headshot/210x210.png", "player_yahoo_id": "32858", "cbs_player_id": "2188356", "player_bye_week": "7", "player_owned_avg": 76.8, "player_owned_espn": 61.5, "player_owned_yahoo": 92, "player_ecr_delta": null, "rank_ecr": 6, "rank_min": "2", "rank_max": "28", "rank_ave": "7.50", "rank_std": "5.45", "pos_rank": "K6", "tier": 2}, {"player_id": 9549, "player_name": "Ryan Succop", "sportsdata_id": "ecc4f0c1-64e0-46cc-9b58-91c2b215e62a", "player_team_id": "TB", "player_position_id": "K", "player_positions": "K", "player_short_name": "R. Succop", "player_eligibility": "K", "player_yahoo_positions": "K", "player_page_url": "https://www.fantasypros.com/nfl/players/ryan-succop.php", "player_filename": "ryan-succop.php", "player_square_image_url": "https://images.fantasypros.com/images/players/nfl/9549/headshot/210x210.png", "player_image_url": "https://images.fantasypros.com/images/players/nfl/9549/headshot/210x210.png", "player_yahoo_id": "9520", "cbs_player_id": "1674148", "player_bye_week": "9", "player_owned_avg": 53.4, "player_owned_espn": 23.8, "player_owned_yahoo": 83, "player_ecr_delta": null, "rank_ecr": 7, "rank_min": "2", "rank_max": "17", "rank_ave": "8.19", "rank_std": "3.34", "pos_rank": "K7", "tier": 2}, {"player_id": 9443, "player_name": "Matt Prater", "sportsdata_id": "67f5e782-f91c-4536-9818-cf4a0e7e821d", "player_team_id": "ARI", "player_position_id": "K", "player_positions": "K", "player_short_name": "M. Prater", "player_eligibility": "K", "player_yahoo_positions": "K", "player_page_url": "https://www.fantasypros.com/nfl/players/matt-prater.php", "player_filename": "matt-prater.php", "player_square_image_url": "https://images.fantasypros.com/images/players/nfl/9443/headshot/210x210.png", "player_image_url": "https://images.fantasypros.com/images/players/nfl/9443/headshot/210x210.png", "player_yahoo_id": "8565", "cbs_player_id": "1109832", "player_bye_week": "12", "player_owned_avg": 24.8, "player_owned_espn": 25.6, "player_owned_yahoo": 24, "player_ecr_delta": null, "rank_ecr": 8, "rank_min": "4", "rank_max": "17", "rank_ave": "9.36", "rank_std": "2.84", "pos_rank": "K8", "tier": 2}, {"player_id": 9534, "player_name": "Robbie Gould", "sportsdata_id": "abd73d50-ce60-47f1-b37f-2f9a05b0d7b9", "player_team_id": "SF", "player_position_id": "K", "player_positions": "K", "player_short_name": "R. Gould", "player_eligibility": "K", "player_yahoo_positions": "K", "player_page_url": "https://www.fantasypros.com/nfl/players/robbie-gould.php", "player_filename": "robbie-gould.php", "player_square_image_url": "https://images.fantasypros.com/images/players/nfl/9534/headshot/210x210.png", "player_image_url": "https://images.fantasypros.com/images/players/nfl/9534/headshot/210x210.png", "player_yahoo_id": "7520", "cbs_player_id": "553121", "player_bye_week": "6", "player_owned_avg": 31.4, "player_owned_espn": 6.8, "player_owned_yahoo": 56, "player_ecr_delta": null, "rank_ecr": 9, "rank_min": "4", "rank_max": "19", "rank_ave": "10.57", "rank_std": "3.25", "pos_rank": "K9", "tier": 3}, {"player_id": 19469, "player_name": "Rodrigo Blankenship", "sportsdata_id": "c8bbff7b-3b6e-413f-8945-24c01bfd84c5", "player_team_id": "IND", "player_position_id": "K", "player_positions": "K", "player_short_name": "R. Blankenship", "player_eligibility": "K", "player_yahoo_positions": "K", "player_page_url": "https://www.fantasypros.com/nfl/players/rodrigo-blankenship.php", "player_filename": "rodrigo-blankenship.php", "player_square_image_url": "https://images.fantasypros.com/images/players/nfl/19469/headshot/210x210.png", "player_image_url": "https://images.fantasypros.com/images/players/nfl/19469/headshot/210x210.png", "player_yahoo_id": "33211", "cbs_player_id": "2183949", "player_bye_week": "14", "player_owned_avg": 46.3, "player_owned_espn": 21.5, "player_owned_yahoo": 71, "player_ecr_delta": null, "rank_ecr": 10, "rank_min": "5", "rank_max": "23", "rank_ave": "10.69", "rank_std": "4.66", "pos_rank": "K10", "tier": 3}, {"player_id": 14003, "player_name": "Jason Myers", "sportsdata_id": "7af4c94b-529b-4403-ab66-2bfed3fcf0c7", "player_team_id": "SEA", "player_position_id": "K", "player_positions": "K", "player_short_name": "J. Myers", "player_eligibility": "K", "player_yahoo_positions": "K", "player_page_url": "https://www.fantasypros.com/nfl/players/jason-myers.php", "player_filename": "jason-myers.php", "player_square_image_url": "https://images.fantasypros.com/images/players/nfl/14003/headshot/210x210.png", "player_image_url": "https://images.fantasypros.com/images/players/nfl/14003/headshot/210x210.png", "player_yahoo_id": "28378", "cbs_player_id": "2169640", "player_bye_week": "9", "player_owned_avg": 56.5, "player_owned_espn": 94.9, "player_owned_yahoo": 18, "player_ecr_delta": null, "rank_ecr": 11, "rank_min": "7", "rank_max": "18", "rank_ave": "11.48", "rank_std": "2.35", "pos_rank": "K11", "tier": 3}, {"player_id": 9433, "player_name": "Mason Crosby", "sportsdata_id": "e0856548-6fd5-4f83-9aa0-91f1bf4cbbd8", "player_team_id": "GB", "player_position_id": "K", "player_positions": "K", "player_short_name": "M. Crosby", "player_eligibility": "K", "player_yahoo_positions": "K", "player_page_url": "https://www.fantasypros.com/nfl/players/mason-crosby.php", "player_filename": "mason-crosby.php", "player_square_image_url": "https://images.fantasypros.com/images/players/nfl/9433/headshot/210x210.png", "player_image_url": "https://images.fantasypros.com/images/players/nfl/9433/headshot/210x210.png", "player_yahoo_id": "8447", "cbs_player_id": "408969", "player_bye_week": "13", "player_owned_avg": 12.2, "player_owned_espn": 6.3, "player_owned_yahoo": 18, "player_ecr_delta": null, "rank_ecr": 12, "rank_min": "6", "rank_max": "20", "rank_ave": "14.21", "rank_std": "3.17", "pos_rank": "K12", "tier": 3}, {"player_id": 17693, "player_name": "Michael Badgley", "sportsdata_id": "375b0d7f-8d03-4111-8c1b-62907f0326a1", "player_team_id": "LAC", "player_position_id": "K", "player_positions": "K", "player_short_name": "M. Badgley", "player_eligibility": "K", "player_yahoo_positions": "K", "player_page_url": "https://www.fantasypros.com/nfl/players/michael-badgley.php", "player_filename": "michael-badgley.php", "player_square_image_url": "https://images.fantasypros.com/images/players/nfl/17693/headshot/210x210.png", "player_image_url": "https://images.fantasypros.com/images/players/nfl/17693/headshot/210x210.png", "player_yahoo_id": "31366", "cbs_player_id": "2925140", "player_bye_week": "7", "player_owned_avg": 11.4, "player_owned_espn": 0.7, "player_owned_yahoo": 22, "player_ecr_delta": null, "rank_ecr": 13, "rank_min": "8", "rank_max": "25", "rank_ave": "14.64", "rank_std": "3.78", "pos_rank": "K13", "tier": 3}, {"player_id": 17420, "player_name": "Daniel Carlson", "sportsdata_id": "7bb70550-c28a-4e47-9a13-cc0c0fef8b38", "player_team_id": "LV", "player_position_id": "K", "player_positions": "K", "player_short_name": "D. Carlson", "player_eligibility": "K", "player_yahoo_positions": "K", "player_page_url": "https://www.fantasypros.com/nfl/players/daniel-carlson.php", "player_filename": "daniel-carlson.php", "player_square_image_url": "https://images.fantasypros.com/images/players/nfl/17420/headshot/210x210.png", "player_image_url": "https://images.fantasypros.com/images/players/nfl/17420/headshot/210x210.png", "player_yahoo_id": "31137", "cbs_player_id": "2079862", "player_bye_week": "8", "player_owned_avg": 12.3, "player_owned_espn": 11.6, "player_owned_yahoo": 13, "player_ecr_delta": null, "rank_ecr": 14, "rank_min": "6", "rank_max": "27", "rank_ave": "15.12", "rank_std": "4.63", "pos_rank": "K14", "tier": 3}, {"player_id": 18545, "player_name": "Matt Gay", "sportsdata_id": "2b90e091-ef78-4753-93eb-0acf3632c206", "player_team_id": "LAR", "player_position_id": "K", "player_positions": "K", "player_short_name": "M. Gay", "player_eligibility": "K", "player_yahoo_positions": "K", "player_page_url": "https://www.fantasypros.com/nfl/players/matt-gay.php", "player_filename": "matt-gay.php", "player_square_image_url": "https://images.fantasypros.com/images/players/nfl/18545/headshot/210x210.png", "player_image_url": "https://images.fantasypros.com/images/players/nfl/18545/headshot/210x210.png", "player_yahoo_id": "31977", "cbs_player_id": "2870511", "player_bye_week": "11", "player_owned_avg": 71.7, "player_owned_espn": 85.3, "player_owned_yahoo": 58, "player_ecr_delta": null, "rank_ecr": 15, "rank_min": "6", "rank_max": "30", "rank_ave": "14.24", "rank_std": "6.33", "pos_rank": "K15", "tier": 3}, {"player_id": 13274, "player_name": "Brandon McManus", "sportsdata_id": "6444feb1-f5a4-4b45-9a45-79308a4445fd", "player_team_id": "DEN", "player_position_id": "K", "player_positions": "K", "player_short_name": "B. McManus", "player_eligibility": "K", "player_yahoo_positions": "K", "player_page_url": "https://www.fantasypros.com/nfl/players/brandon-mcmanus.php", "player_filename": "brandon-mcmanus.php", "player_square_image_url": "https://images.fantasypros.com/images/players/nfl/13274/headshot/210x210.png", "player_image_url": "https://images.fantasypros.com/images/players/nfl/13274/headshot/210x210.png", "player_yahoo_id": "27120", "cbs_player_id": "2058320", "player_bye_week": "11", "player_owned_avg": 49.3, "player_owned_espn": 87.5, "player_owned_yahoo": 11, "player_ecr_delta": null, "rank_ecr": 16, "rank_min": "8", "rank_max": "25", "rank_ave": "17.19", "rank_std": "3.51", "pos_rank": "K16", "tier": 3}, {"player_id": 19028, "player_name": "Joey Slye", "sportsdata_id": "ef4998e0-c9ef-4afe-88ab-d09b48975a08", "player_team_id": "CAR", "player_position_id": "K", "player_positions": "K", "player_short_name": "J. Slye", "player_eligibility": "K", "player_yahoo_positions": "K", "player_page_url": "https://www.fantasypros.com/nfl/players/joey-slye.php", "player_filename": "joey-slye.php", "player_square_image_url": "https://images.fantasypros.com/images/players/nfl/19028/headshot/210x210.png", "player_image_url": "https://images.fantasypros.com/images/players/nfl/19028/headshot/210x210.png", "player_yahoo_id": "32384", "cbs_player_id": "3116871", "player_bye_week": "13", "player_owned_avg": 3.3, "player_owned_espn": 1.6, "player_owned_yahoo": 5, "player_ecr_delta": null, "rank_ecr": 17, "rank_min": "12", "rank_max": "26", "rank_ave": "18.26", "rank_std": "3.63", "pos_rank": "K17", "tier": 4}, {"player_id": 16026, "player_name": "Wil Lutz", "sportsdata_id": "c4cf84d0-6022-4ac1-a9ba-85587921c53f", "player_team_id": "NO", "player_position_id": "K", "player_positions": "K", "player_short_name": "W. Lutz", "player_eligibility": "K", "player_yahoo_positions": "K", "player_page_url": "https://www.fantasypros.com/nfl/players/wil-lutz.php", "player_filename": "wil-lutz.php", "player_square_image_url": "https://images.fantasypros.com/images/players/nfl/16026/headshot/210x210.png", "player_image_url": "https://images.fantasypros.com/images/players/nfl/16026/headshot/210x210.png", "player_yahoo_id": "29754", "cbs_player_id": "2008545", "player_bye_week": "6", "player_owned_avg": 21.3, "player_owned_espn": 7.5, "player_owned_yahoo": 35, "player_ecr_delta": -3, "rank_ecr": 18, "rank_min": "4", "rank_max": "33", "rank_ave": "17.71", "rank_std": "8.85", "pos_rank": "K18", "tier": 4}, {"player_id": 11818, "player_name": "Dustin Hopkins", "sportsdata_id": "058c99fc-470c-4579-a165-03e043335cc1", "player_team_id": "WAS", "player_position_id": "K", "player_positions": "K", "player_short_name": "D. Hopkins", "player_eligibility": "K", "player_yahoo_positions": "K", "player_page_url": "https://www.fantasypros.com/nfl/players/dustin-hopkins.php", "player_filename": "dustin-hopkins.php", "player_square_image_url": "https://images.fantasypros.com/images/players/nfl/11818/headshot/210x210.png", "player_image_url": "https://images.fantasypros.com/images/players/nfl/11818/headshot/210x210.png", "player_yahoo_id": "26800", "cbs_player_id": "1664151", "player_bye_week": "9", "player_owned_avg": 4.9, "player_owned_espn": 2.7, "player_owned_yahoo": 7, "player_ecr_delta": null, "rank_ecr": 19, "rank_min": "12", "rank_max": "28", "rank_ave": "20.39", "rank_std": "3.91", "pos_rank": "K19", "tier": 4}, {"player_id": 16540, "player_name": "Jake Elliott", "sportsdata_id": "059e5bb7-1842-4558-9aaf-77c352a21216", "player_team_id": "PHI", "player_position_id": "K", "player_positions": "K", "player_short_name": "J. Elliott", "player_eligibility": "K", "player_yahoo_positions": "K", "player_page_url": "https://www.fantasypros.com/nfl/players/jake-elliott.php", "player_filename": "jake-elliott.php", "player_square_image_url": "https://images.fantasypros.com/images/players/nfl/16540/headshot/210x210.png", "player_image_url": "https://images.fantasypros.com/images/players/nfl/16540/headshot/210x210.png", "player_yahoo_id": "30266", "cbs_player_id": "2080295", "player_bye_week": "14", "player_owned_avg": 2.7, "player_owned_espn": 1.3, "player_owned_yahoo": 4, "player_ecr_delta": null, "rank_ecr": 20, "rank_min": "6", "rank_max": "30", "rank_ave": "19.83", "rank_std": "5.35", "pos_rank": "K20", "tier": 4}, {"player_id": 13029, "player_name": "Chris Boswell", "sportsdata_id": "441eb531-1ec8-4f65-9174-78bc6adada63", "player_team_id": "PIT", "player_position_id": "K", "player_positions": "K", "player_short_name": "C. Boswell", "player_eligibility": "K", "player_yahoo_positions": "K", "player_page_url": "https://www.fantasypros.com/nfl/players/chris-boswell.php", "player_filename": "chris-boswell.php", "player_square_image_url": "https://images.fantasypros.com/images/players/nfl/13029/headshot/210x210.png", "player_image_url": "https://images.fantasypros.com/images/players/nfl/13029/headshot/210x210.png", "player_yahoo_id": "28188", "cbs_player_id": "1724930", "player_bye_week": "7", "player_owned_avg": 4.2, "player_owned_espn": 2.4, "player_owned_yahoo": 6, "player_ecr_delta": null, "rank_ecr": 21, "rank_min": "14", "rank_max": "28", "rank_ave": "20.05", "rank_std": "2.93", "pos_rank": "K21", "tier": 4}, {"player_id": 14327, "player_name": "Josh Lambo", "sportsdata_id": "69bdf41e-3c32-46c1-93b8-e952edf5c61d", "player_team_id": "JAC", "player_position_id": "K", "player_positions": "K", "player_short_name": "J. Lambo", "player_eligibility": "K", "player_yahoo_positions": "K", "player_page_url": "https://www.fantasypros.com/nfl/players/josh-lambo.php", "player_filename": "josh-lambo.php", "player_square_image_url": "https://images.fantasypros.com/images/players/nfl/14327/headshot/210x210.png", "player_image_url": "https://images.fantasypros.com/images/players/nfl/14327/headshot/210x210.png", "player_yahoo_id": "28685", "cbs_player_id": "2013049", "player_bye_week": "7", "player_owned_avg": 16.3, "player_owned_espn": 27.5, "player_owned_yahoo": 5, "player_ecr_delta": null, "rank_ecr": 22, "rank_min": "14", "rank_max": "31", "rank_ave": "23.44", "rank_std": "3.93", "pos_rank": "K22", "tier": 4}, {"player_id": 15756, "player_name": "Ka'imi Fairbairn", "sportsdata_id": "203b60aa-cb94-499c-a4ca-d3c6b94dddc4", "player_team_id": "HOU", "player_position_id": "K", "player_positions": "K", "player_short_name": "K. Fairbairn", "player_eligibility": "K", "player_yahoo_positions": "K", "player_page_url": "https://www.fantasypros.com/nfl/players/kaimi-fairbairn.php", "player_filename": "kaimi-fairbairn.php", "player_square_image_url": "https://images.fantasypros.com/images/players/nfl/15756/headshot/210x210.png", "player_image_url": "https://images.fantasypros.com/images/players/nfl/15756/headshot/210x210.png", "player_yahoo_id": "29792", "cbs_player_id": "1996562", "player_bye_week": "10", "player_owned_avg": 1.8, "player_owned_espn": 1.6, "player_owned_yahoo": 2, "player_ecr_delta": 3, "rank_ecr": 23, "rank_min": "8", "rank_max": "33", "rank_ave": "23.00", "rank_std": "6.10", "pos_rank": "K23", "tier": 4}, {"player_id": 9232, "player_name": "Graham Gano", "sportsdata_id": "63f8a401-f308-4463-9d0b-4335b98da682", "player_team_id": "NYG", "player_position_id": "K", "player_positions": "K", "player_short_name": "G. Gano", "player_eligibility": "K", "player_yahoo_positions": "K", "player_page_url": "https://www.fantasypros.com/nfl/players/graham-gano.php", "player_filename": "graham-gano.php", "player_square_image_url": "https://images.fantasypros.com/images/players/nfl/9232/headshot/210x210.png", "player_image_url": "https://images.fantasypros.com/images/players/nfl/9232/headshot/210x210.png", "player_yahoo_id": "9526", "cbs_player_id": "558839", "player_bye_week": "10", "player_owned_avg": 38.2, "player_owned_espn": 73.3, "player_owned_yahoo": 3, "player_ecr_delta": null, "rank_ecr": 24, "rank_min": "14", "rank_max": "32", "rank_ave": "23.22", "rank_std": "3.88", "pos_rank": "K24", "tier": 4}, {"player_id": 13731, "player_name": "Cairo Santos", "sportsdata_id": "d96ff17c-841a-4768-8e08-3a4cfcb7f717", "player_team_id": "CHI", "player_position_id": "K", "player_positions": "K", "player_short_name": "C. Santos", "player_eligibility": "K", "player_yahoo_positions": "K", "player_page_url": "https://www.fantasypros.com/nfl/players/cairo-santos.php", "player_filename": "cairo-santos.php", "player_square_image_url": "https://images.fantasypros.com/images/players/nfl/13731/headshot/210x210.png", "player_image_url": "https://images.fantasypros.com/images/players/nfl/13731/headshot/210x210.png", "player_yahoo_id": "28227", "cbs_player_id": "2132690", "player_bye_week": "10", "player_owned_avg": 2.5, "player_owned_espn": 2, "player_owned_yahoo": 3, "player_ecr_delta": null, "rank_ecr": 25, "rank_min": "12", "rank_max": "35", "rank_ave": "23.97", "rank_std": "5.91", "pos_rank": "K25", "tier": 5}, {"player_id": 13806, "player_name": "Cody Parkey", "sportsdata_id": "4b99ead5-0f79-4899-84a7-075c08890698", "player_team_id": "CLE", "player_position_id": "K", "player_positions": "K", "player_short_name": "C. Parkey", "player_eligibility": "K", "player_yahoo_positions": "K", "player_page_url": "https://www.fantasypros.com/nfl/players/cody-parkey.php", "player_filename": "cody-parkey.php", "player_square_image_url": "https://images.fantasypros.com/images/players/nfl/13806/headshot/210x210.png", "player_image_url": "https://images.fantasypros.com/images/players/nfl/13806/headshot/210x210.png", "player_yahoo_id": "27911", "cbs_player_id": "2130323", "player_bye_week": "13", "player_owned_avg": 6.5, "player_owned_espn": 9.9, "player_owned_yahoo": 3, "player_ecr_delta": null, "rank_ecr": 26, "rank_min": "13", "rank_max": "32", "rank_ave": "22.77", "rank_std": "4.59", "pos_rank": "K26", "tier": 5}, {"player_id": 9491, "player_name": "Nick Folk", "sportsdata_id": "b37c621e-1125-4c35-bea0-fcabb1527060", "player_team_id": "NE", "player_position_id": "K", "player_positions": "K", "player_short_name": "N. Folk", "player_eligibility": "K", "player_yahoo_positions": "K", "player_page_url": "https://www.fantasypros.com/nfl/players/nick-folk.php", "player_filename": "nick-folk.php", "player_square_image_url": "https://images.fantasypros.com/images/players/nfl/9491/headshot/210x210.png", "player_image_url": "https://images.fantasypros.com/images/players/nfl/9491/headshot/210x210.png", "player_yahoo_id": "8432", "cbs_player_id": "410721", "player_bye_week": "14", "player_owned_avg": 18.7, "player_owned_espn": 4.3, "player_owned_yahoo": 33, "player_ecr_delta": null, "rank_ecr": 27, "rank_min": "18", "rank_max": "37", "rank_ave": "26.75", "rank_std": "5.25", "pos_rank": "K27", "tier": 5}, {"player_id": 11339, "player_name": "Randy Bullock", "sportsdata_id": "c7d8781f-b9f6-4e0f-b0b6-29fce3985f3e", "player_team_id": "DET", "player_position_id": "K", "player_positions": "K", "player_short_name": "R. Bullock", "player_eligibility": "K", "player_yahoo_positions": "K", "player_page_url": "https://www.fantasypros.com/nfl/players/randy-bullock.php", "player_filename": "randy-bullock.php", "player_square_image_url": "https://images.fantasypros.com/images/players/nfl/11339/headshot/210x210.png", "player_image_url": "https://images.fantasypros.com/images/players/nfl/11339/headshot/210x210.png", "player_yahoo_id": "25871", "cbs_player_id": "1632503", "player_bye_week": "9", "player_owned_avg": 0.9, "player_owned_espn": 0.7, "player_owned_yahoo": 1, "player_ecr_delta": null, "rank_ecr": 28, "rank_min": "21", "rank_max": "34", "rank_ave": "28.77", "rank_std": "3.00", "pos_rank": "K28", "tier": 5}, {"player_id": 23297, "player_name": "Evan McPherson", "sportsdata_id": "acc143ed-53b2-49c9-81bc-16e6c98ffcae", "player_team_id": "CIN", "player_position_id": "K", "player_positions": "K", "player_short_name": "E. McPherson", "player_eligibility": "K", "player_yahoo_positions": "K", "player_page_url": "https://www.fantasypros.com/nfl/players/evan-mcpherson.php", "player_filename": "evan-mcpherson.php", "player_square_image_url": "", "player_image_url": "", "player_yahoo_id": "33537", "cbs_player_id": "2962681", "player_bye_week": "10", "player_owned_avg": 2.1, "player_owned_espn": 2.2, "player_owned_yahoo": 2, "player_ecr_delta": null, "rank_ecr": 29, "rank_min": "12", "rank_max": "36", "rank_ave": "25.67", "rank_std": "5.71", "pos_rank": "K29", "tier": 5}, {"player_id": 17647, "player_name": "Greg Joseph", "sportsdata_id": "a2aab80d-174c-4639-beac-e2b70bb3625f", "player_team_id": "MIN", "player_position_id": "K", "player_positions": "K", "player_short_name": "G. Joseph", "player_eligibility": "K", "player_yahoo_positions": "K", "player_page_url": "https://www.fantasypros.com/nfl/players/greg-joseph.php", "player_filename": "greg-joseph.php", "player_square_image_url": "https://images.fantasypros.com/images/players/nfl/17647/headshot/210x210.png", "player_image_url": "https://images.fantasypros.com/images/players/nfl/17647/headshot/210x210.png", "player_yahoo_id": "31538", "cbs_player_id": "2926810", "player_bye_week": "7", "player_owned_avg": 0.7, "player_owned_espn": 0.4, "player_owned_yahoo": 1, "player_ecr_delta": null, "rank_ecr": 30, "rank_min": "18", "rank_max": "35", "rank_ave": "25.41", "rank_std": "5.08", "pos_rank": "K30", "tier": 5}, {"player_id": 18689, "player_name": "Austin Seibert", "sportsdata_id": "bd1f047a-978f-4643-b55f-f4d3b0719a4e", "player_team_id": "CIN", "player_position_id": "K", "player_positions": "K", "player_short_name": "A. Seibert", "player_eligibility": "K", "player_yahoo_positions": "K", "player_page_url": "https://www.fantasypros.com/nfl/players/austin-seibert.php", "player_filename": "austin-seibert.php", "player_square_image_url": "https://images.fantasypros.com/images/players/nfl/18689/headshot/210x210.png", "player_image_url": "https://images.fantasypros.com/images/players/nfl/18689/headshot/210x210.png", "player_yahoo_id": "32002", "cbs_player_id": "2179668", "player_bye_week": "10", "player_owned_avg": 0.1, "player_owned_espn": 0.1, "player_owned_yahoo": 0, "player_ecr_delta": null, "rank_ecr": 31, "rank_min": "20", "rank_max": "36", "rank_ave": "27.25", "rank_std": "4.61", "pos_rank": "K31", "tier": 5}, {"player_id": 16319, "player_name": "Sam Ficken", "sportsdata_id": "f61e6429-3f9b-478c-8697-e00fe813ce9c", "player_team_id": "TEN", "player_position_id": "K", "player_positions": "K", "player_short_name": "S. Ficken", "player_eligibility": "K", "player_yahoo_positions": "K", "player_page_url": "https://www.fantasypros.com/nfl/players/sam-ficken.php", "player_filename": "sam-ficken.php", "player_square_image_url": "https://images.fantasypros.com/images/players/nfl/16319/headshot/210x210.png", "player_image_url": "https://images.fantasypros.com/images/players/nfl/16319/headshot/210x210.png", "player_yahoo_id": "30038", "cbs_player_id": "1889916", "player_bye_week": "13", "player_owned_avg": 0.3, "player_owned_espn": 0.3, "player_owned_yahoo": 0, "player_ecr_delta": null, "rank_ecr": 32, "rank_min": "12", "rank_max": "38", "rank_ave": "26.53", "rank_std": "7.72", "pos_rank": "K32", "tier": 5}, {"player_id": 19765, "player_name": "Tucker McCann", "sportsdata_id": "397901eb-5589-4f0e-8c02-f50509e22f3c", "player_team_id": "TEN", "player_position_id": "K", "player_positions": "K", "player_short_name": "T. McCann", "player_eligibility": "K", "player_yahoo_positions": "K", "player_page_url": "https://www.fantasypros.com/nfl/players/tucker-mccann.php", "player_filename": "tucker-mccann.php", "player_square_image_url": "https://images.fantasypros.com/images/players/nfl/19765/headshot/210x210.png", "player_image_url": "https://images.fantasypros.com/images/players/nfl/19765/headshot/210x210.png", "player_yahoo_id": "33343", "cbs_player_id": "3161134", "player_bye_week": "13", "player_owned_avg": 0.3, "player_owned_espn": 0.3, "player_owned_yahoo": 0, "player_ecr_delta": null, "rank_ecr": 33, "rank_min": "21", "rank_max": "34", "rank_ave": "28.76", "rank_std": "4.08", "pos_rank": "K33", "tier": 5}, {"player_id": 9573, "player_name": "Stephen Gostkowski", "sportsdata_id": "a527b7db-0b52-4379-9e4c-2e08c1fe1bed", "player_team_id": "FA", "player_position_id": "K", "player_positions": "K", "player_short_name": "S. Gostkowski", "player_eligibility": "K", "player_yahoo_positions": "K", "player_page_url": "https://www.fantasypros.com/nfl/players/stephen-gostkowski.php", "player_filename": "stephen-gostkowski.php", "player_square_image_url": "https://images.fantasypros.com/images/players/nfl/9573/headshot/210x210.png", "player_image_url": "https://images.fantasypros.com/images/players/nfl/9573/headshot/210x210.png", "player_yahoo_id": "7867", "cbs_player_id": "411579", "player_bye_week": null, "player_owned_avg": 0.7, "player_owned_espn": 0.3, "player_owned_yahoo": 1, "player_ecr_delta": null, "rank_ecr": 34, "rank_min": "22", "rank_max": "37", "rank_ave": "29.63", "rank_std": "4.72", "pos_rank": "K34", "tier": 5}, {"player_id": 16548, "player_name": "Zane Gonzalez", "sportsdata_id": "cd0f4ef0-9914-4125-be4d-804a72350ceb", "player_team_id": "DET", "player_position_id": "K", "player_positions": "K", "player_short_name": "Z. Gonzalez", "player_eligibility": "K", "player_yahoo_positions": "K", "player_page_url": "https://www.fantasypros.com/nfl/players/zane-gonzalez.php", "player_filename": "zane-gonzalez.php", "player_square_image_url": "https://images.fantasypros.com/images/players/nfl/16548/headshot/210x210.png", "player_image_url": "https://images.fantasypros.com/images/players/nfl/16548/headshot/210x210.png", "player_yahoo_id": "30337", "cbs_player_id": "2061033", "player_bye_week": "9", "player_owned_avg": 1.1, "player_owned_espn": 0.1, "player_owned_yahoo": 2, "player_ecr_delta": null, "rank_ecr": 35, "rank_min": "11", "rank_max": "38", "rank_ave": "25.33", "rank_std": "9.06", "pos_rank": "K35", "tier": 5}, {"player_id": 19762, "player_name": "Sam Sloman", "sportsdata_id": "e44cc736-fe98-4b80-a138-4ebc5f087335", "player_team_id": "PIT", "player_position_id": "K", "player_positions": "K", "player_short_name": "S. Sloman", "player_eligibility": "K", "player_yahoo_positions": "K", "player_page_url": "https://www.fantasypros.com/nfl/players/sam-sloman.php", "player_filename": "sam-sloman.php", "player_square_image_url": "https://images.fantasypros.com/images/players/nfl/19762/headshot/210x210.png", "player_image_url": "https://images.fantasypros.com/images/players/nfl/19762/headshot/210x210.png", "player_yahoo_id": "32918", "cbs_player_id": "2240109", "player_bye_week": "7", "player_owned_avg": 0, "player_owned_espn": 0, "player_owned_yahoo": 0, "player_ecr_delta": null, "rank_ecr": 36, "rank_min": "24", "rank_max": "40", "rank_ave": "30.63", "rank_std": "4.61", "pos_rank": "K36", "tier": 5}, {"player_id": 10970, "player_name": "Dan Bailey", "sportsdata_id": "beb64618-614c-49f7-a3aa-c0c75b7839ea", "player_team_id": "FA", "player_position_id": "K", "player_positions": "K", "player_short_name": "D. Bailey", "player_eligibility": "K", "player_yahoo_positions": "K", "player_page_url": "https://www.fantasypros.com/nfl/players/dan-bailey.php", "player_filename": "dan-bailey.php", "player_square_image_url": "https://images.fantasypros.com/images/players/nfl/10970/headshot/210x210.png", "player_image_url": "https://images.fantasypros.com/images/players/nfl/10970/headshot/210x210.png", "player_yahoo_id": "25427", "cbs_player_id": "1689664", "player_bye_week": null, "player_owned_avg": 0.6, "player_owned_espn": 0.1, "player_owned_yahoo": 1, "player_ecr_delta": null, "rank_ecr": 37, "rank_min": "12", "rank_max": "43", "rank_ave": "26.75", "rank_std": "8.82", "pos_rank": "K37", "tier": 6}, {"player_id": 23462, "player_name": "Chris Naggar", "sportsdata_id": "0cddffa4-a061-497d-a487-359e66744416", "player_team_id": "NYJ", "player_position_id": "K", "player_positions": "K", "player_short_name": "C. Naggar", "player_eligibility": "K", "player_yahoo_positions": "K", "player_page_url": "https://www.fantasypros.com/nfl/players/chris-naggar.php", "player_filename": "chris-naggar.php", "player_square_image_url": "", "player_image_url": "", "player_yahoo_id": "33700", "cbs_player_id": "2803493", "player_bye_week": "6", "player_owned_avg": 0, "player_owned_espn": 0, "player_owned_yahoo": 0, "player_ecr_delta": null, "rank_ecr": 38, "rank_min": "29", "rank_max": "41", "rank_ave": "33.56", "rank_std": "3.56", "pos_rank": "K38", "tier": 6}, {"player_id": 16072, "player_name": "Aldrick Rosas", "sportsdata_id": "8fb2ca06-3d13-4552-98e0-7b913b4ab5b9", "player_team_id": "JAC", "player_position_id": "K", "player_positions": "K", "player_short_name": "A. Rosas", "player_eligibility": "K", "player_yahoo_positions": "K", "player_page_url": "https://www.fantasypros.com/nfl/players/aldrick-rosas.php", "player_filename": "aldrick-rosas.php", "player_square_image_url": "https://images.fantasypros.com/images/players/nfl/16072/headshot/210x210.png", "player_image_url": "https://images.fantasypros.com/images/players/nfl/16072/headshot/210x210.png", "player_yahoo_id": "29949", "cbs_player_id": "2237139", "player_bye_week": "7", "player_owned_avg": 0, "player_owned_espn": 0, "player_owned_yahoo": 0, "player_ecr_delta": null, "rank_ecr": 39, "rank_min": "19", "rank_max": "39", "rank_ave": "29.50", "rank_std": "7.23", "pos_rank": "K39", "tier": 6}, {"player_id": 12378, "player_name": "Brett Maher", "sportsdata_id": "99c9de87-7fe1-4d5e-928e-586f48af2d79", "player_team_id": "NO", "player_position_id": "K", "player_positions": "K", "player_short_name": "B. Maher", "player_eligibility": "K", "player_yahoo_positions": "K", "player_page_url": "https://www.fantasypros.com/nfl/players/brett-maher.php", "player_filename": "brett-maher.php", "player_square_image_url": "https://images.fantasypros.com/images/players/nfl/12378/headshot/210x210.png", "player_image_url": "https://images.fantasypros.com/images/players/nfl/12378/headshot/210x210.png", "player_yahoo_id": "27369", "cbs_player_id": "1630817", "player_bye_week": "6", "player_owned_avg": 0.1, "player_owned_espn": 0.1, "player_owned_yahoo": 0, "player_ecr_delta": null, "rank_ecr": 40, "rank_min": "30", "rank_max": "44", "rank_ave": "35.83", "rank_std": "4.74", "pos_rank": "K40", "tier": 6}, {"player_id": 19766, "player_name": "Matt Ammendola", "sportsdata_id": "f6d943d7-3ddb-4054-8796-9febf6026898", "player_team_id": "NYJ", "player_position_id": "K", "player_positions": "K", "player_short_name": "M. Ammendola", "player_eligibility": "K", "player_yahoo_positions": "K", "player_page_url": "https://www.fantasypros.com/nfl/players/matt-ammendola.php", "player_filename": "matt-ammendola.php", "player_square_image_url": "", "player_image_url": "", "player_yahoo_id": "33381", "cbs_player_id": "2185684", "player_bye_week": "6", "player_owned_avg": 0, "player_owned_espn": 0, "player_owned_yahoo": 0, "player_ecr_delta": null, "rank_ecr": 41, "rank_min": "31", "rank_max": "41", "rank_ave": "34.67", "rank_std": "4.50", "pos_rank": "K41", "tier": 6}, {"player_id": 19058, "player_name": "Chase McLaughlin", "sportsdata_id": "12d28404-63e1-432f-adde-c93631a5c39c", "player_team_id": "CLE", "player_position_id": "K", "player_positions": "K", "player_short_name": "C. McLaughlin", "player_eligibility": "K", "player_yahoo_positions": "K", "player_page_url": "https://www.fantasypros.com/nfl/players/chase-mclaughlin.php", "player_filename": "chase-mclaughlin.php", "player_square_image_url": "https://images.fantasypros.com/images/players/nfl/19058/headshot/210x210.png", "player_image_url": "https://images.fantasypros.com/images/players/nfl/19058/headshot/210x210.png", "player_yahoo_id": "32417", "cbs_player_id": "2165272", "player_bye_week": "13", "player_owned_avg": 0.1, "player_owned_espn": 0.1, "player_owned_yahoo": 0, "player_ecr_delta": null, "rank_ecr": 42, "rank_min": "29", "rank_max": "42", "rank_ave": "36.33", "rank_std": "5.44", "pos_rank": "K42", "tier": 6}, {"player_id": 23370, "player_name": "Riley Patterson", "sportsdata_id": "deac735c-af0a-4f01-ada8-379ef66917ba", "player_team_id": "MIN", "player_position_id": "K", "player_positions": "K", "player_short_name": "R. Patterson", "player_eligibility": "K", "player_yahoo_positions": "K", "player_page_url": "https://www.fantasypros.com/nfl/players/riley-patterson.php", "player_filename": "riley-patterson.php", "player_square_image_url": "", "player_image_url": "", "player_yahoo_id": "33781", "cbs_player_id": "2865368", "player_bye_week": "7", "player_owned_avg": 0, "player_owned_espn": 0, "player_owned_yahoo": 0, "player_ecr_delta": null, "rank_ecr": 43, "rank_min": "40", "rank_max": "43", "rank_ave": "41.67", "rank_std": "1.25", "pos_rank": "K43", "tier": 6}]}